{"type": "Feature", "id": 12524421, "properties": {"woe:id": 12524421, "woe:parent_id": 161844, "woe:name": "Miquelon Airport", "woe:placetype": 14, "woe:placetype_name": "Airport", "woe:lang": "ENG", "iso:country": "PM", "meta:provider": ["geoplanet:7.3.1", "geoplanet:7.3.2", "geoplanet:7.4.0", "geoplanet:7.4.1", "geoplanet:7.5.1", "geoplanet:7.5.2", "geoplanet:7.6.0", "geoplanet:7.8.1", "geoplanet:7.9.0", "geoplanet:7.10.0", "geoplanet:8.0.0", "woeplanet:8.0.0"], "meta:indexed": "2020-08-20T20:56:33.217613", "woe:alias_ENG_V": ["MQC Airport", "MQC"], "meta:updated": "2020-08-22T02:50:45.023142", "woe:hierarchy": {"continent": 24865672, "country": 23424939, "town": 0, "planet": 1, "county": 0, "suburb": 0, "state": 24549864, "region": 0, "localadmin": 0}, "woe:timezone_id": 28350776, "woe:hash": "f8ruhuqgmu5s", "woe:centroid": [-56.383301, 47.133301], "geom:latitude": 47.133301, "geom:longitude": -56.383301, "geom:hash": "f8ruhuqgmu5s", "woe:latitude": 47.133301, "geom:centroid": [-56.383301, 47.133301], "woe:longitude": -56.383301, "woe:repo": "woeplanet-airport-pm"}, "geometry": {"coordinates": [-56.383301, 47.133301], "type": "Point"}}